MANIFEST.in
README.rst
setup.py
django_smartadmin.egg-info/PKG-INFO
django_smartadmin.egg-info/SOURCES.txt
django_smartadmin.egg-info/dependency_links.txt
django_smartadmin.egg-info/requires.txt
django_smartadmin.egg-info/top_level.txt
smartadmin/__init__.py
smartadmin/admin.py