Metadata-Version: 1.0
Name: django-smartadmin
Version: 0.0.4
Summary: Django ModelAdmin for the lazy.
Home-page: https://github.com/0101/django-smartadmin/
Author: Petr Pokorny
Author-email: petr@innit.cz
License: MIT
Platform: UNKNOWN
